bifacialvf/__init__.py
bifacialvf/bifacialvf.py
bifacialvf/loadVFresults.py
bifacialvf/readepw.py
bifacialvf/sun.py
bifacialvf/vf.py
bifacialvf/data/722740TYA.CSV
bifacialvf/data/724010TYA.CSV
bifacialvf/data/724666TYA.CSV
bifacialvf/data/USA_VA_Richmond.Intl.AP.724010_TMY.epw
bifacialvf-0.1.7.dist-info/LICENSE
bifacialvf-0.1.7.dist-info/METADATA
bifacialvf-0.1.7.dist-info/WHEEL
bifacialvf-0.1.7.dist-info/top_level.txt
bifacialvf-0.1.7.dist-info/RECORD
