Metadata-Version: 2.1
Name: bifacialvf
Version: 0.1.7
Summary: Bifacial PV system evaluation using view factor method
Home-page: https://github.com/NREL/bifacialvf
Author: Chris Deline
Author-email: chris.deline@nrel.gov
License: BSD
Keywords: bifacial view factor photovoltaics pv
Platform: UNKNOWN
Classifier: Development Status :: 4 - Beta
Classifier: Intended Audience :: Science/Research
Classifier: License :: OSI Approved :: BSD License
Classifier: Programming Language :: Python :: 2.7
Classifier: Programming Language :: Python :: 3.6
Requires-Dist: numpy
Requires-Dist: pvlib (>=0.5.0)
